ledgerkeeper/__init__.py
ledgerkeeper/ledgerAccess.py
ledgerkeeper-0.3.dist-info/LICENSE
ledgerkeeper-0.3.dist-info/METADATA
ledgerkeeper-0.3.dist-info/WHEEL
ledgerkeeper-0.3.dist-info/top_level.txt
ledgerkeeper-0.3.dist-info/RECORD
